enciphey.py
enciphey-0.1.2.dist-info/LICENSE
enciphey-0.1.2.dist-info/WHEEL
enciphey-0.1.2.dist-info/METADATA
enciphey-0.1.2.dist-info/RECORD
