Metadata-Version: 2.1
Name: enciphey
Version: 0.1.2
Summary: Randomly chooses an encryption
License: MIT
Author: Brandon
Author-email: brandon@skerritt.blog
Requires-Python: >=3.8,<4.0
Classifier: License :: OSI Approved :: MIT License
Classifier: Programming Language :: Python :: 3
Classifier: Programming Language :: Python :: 3.8
Requires-Dist: cipheycore (>=0.1.5-rc.4,<0.2.0)
Requires-Dist: cipheydists (>=0.1.3,<0.2.0)
Requires-Dist: unicode (>=2.7,<3.0)
